<?xml version="1.0" ?>
<rooms>
	<room variant="0" name="Ferrium - PORTRAITS" type="1" subtype="0" shape="1" width="13" height="7" difficulty="5" weight="0.0">
		<door exists="False" x="-1" y="3"/>
		<door exists="False" x="6" y="-1"/>
		<door exists="False" x="6" y="7"/>
		<door exists="False" x="13" y="3"/>
		<spawn x="0" y="0">
			<entity type="12005" variant="1" subtype="0" weight="1.0"/>
		</spawn>
		<spawn x="1" y="0">
			<entity type="12005" variant="1" subtype="1" weight="1.0"/>
		</spawn>
		<spawn x="2" y="0">
			<entity type="12005" variant="1" subtype="2" weight="1.0"/>
		</spawn>
		<spawn x="3" y="0">
			<entity type="12005" variant="1" subtype="3" weight="1.0"/>
		</spawn>
		<spawn x="4" y="0">
			<entity type="12005" variant="1" subtype="4" weight="1.0"/>
		</spawn>
		<spawn x="5" y="0">
			<entity type="12005" variant="1" subtype="5" weight="1.0"/>
		</spawn>
		<spawn x="6" y="0">
			<entity type="12006" variant="0" subtype="4" weight="1.0"/>
		</spawn>
		<spawn x="7" y="0">
			<entity type="12004" variant="133" subtype="326" weight="1.0"/>
		</spawn>
		<spawn x="8" y="0">
			<entity type="12004" variant="133" subtype="327" weight="1.0"/>
		</spawn>
		<spawn x="9" y="0">
			<entity type="12004" variant="133" subtype="328" weight="1.0"/>
		</spawn>
		<spawn x="10" y="0">
			<entity type="12004" variant="133" subtype="329" weight="1.0"/>
		</spawn>
		<spawn x="11" y="0">
			<entity type="12004" variant="133" subtype="330" weight="1.0"/>
		</spawn>
		<spawn x="12" y="0">
			<entity type="12004" variant="133" subtype="331" weight="1.0"/>
		</spawn>
		<spawn x="6" y="1">
			<entity type="12006" variant="0" subtype="4" weight="1.0"/>
		</spawn>
		<spawn x="6" y="2">
			<entity type="12006" variant="0" subtype="4" weight="1.0"/>
		</spawn>
		<spawn x="11" y="2">
			<entity type="12000" variant="2601" subtype="532" weight="1.0"/>
		</spawn>
		<spawn x="6" y="3">
			<entity type="12006" variant="0" subtype="4" weight="1.0"/>
		</spawn>
		<spawn x="1" y="4">
			<entity type="12001" variant="0" subtype="0" weight="1.0"/>
		</spawn>
		<spawn x="6" y="4">
			<entity type="12006" variant="0" subtype="4" weight="1.0"/>
		</spawn>
		<spawn x="7" y="4">
			<entity type="12006" variant="0" subtype="20" weight="1.0"/>
		</spawn>
		<spawn x="10" y="4">
			<entity type="12006" variant="0" subtype="20" weight="1.0"/>
		</spawn>
		<spawn x="11" y="4">
			<entity type="12006" variant="0" subtype="16" weight="1.0"/>
		</spawn>
		<spawn x="12" y="4">
			<entity type="12006" variant="0" subtype="20" weight="1.0"/>
		</spawn>
		<spawn x="6" y="5">
			<entity type="12006" variant="0" subtype="4" weight="1.0"/>
		</spawn>
		<spawn x="0" y="6">
			<entity type="12004" variant="133" subtype="320" weight="1.0"/>
		</spawn>
		<spawn x="1" y="6">
			<entity type="12004" variant="133" subtype="321" weight="1.0"/>
		</spawn>
		<spawn x="2" y="6">
			<entity type="12004" variant="133" subtype="322" weight="1.0"/>
		</spawn>
		<spawn x="3" y="6">
			<entity type="12004" variant="133" subtype="323" weight="1.0"/>
		</spawn>
		<spawn x="4" y="6">
			<entity type="12004" variant="133" subtype="324" weight="1.0"/>
		</spawn>
		<spawn x="5" y="6">
			<entity type="12004" variant="133" subtype="325" weight="1.0"/>
		</spawn>
		<spawn x="6" y="6">
			<entity type="12006" variant="0" subtype="4" weight="1.0"/>
		</spawn>
		<spawn x="7" y="6">
			<entity type="12005" variant="1" subtype="6" weight="1.0"/>
		</spawn>
		<spawn x="8" y="6">
			<entity type="12005" variant="1" subtype="7" weight="1.0"/>
		</spawn>
		<spawn x="9" y="6">
			<entity type="12005" variant="1" subtype="8" weight="1.0"/>
		</spawn>
		<spawn x="10" y="6">
			<entity type="12005" variant="1" subtype="9" weight="1.0"/>
		</spawn>
		<spawn x="11" y="6">
			<entity type="12005" variant="1" subtype="10" weight="1.0"/>
		</spawn>
		<spawn x="12" y="6">
			<entity type="12005" variant="1" subtype="11" weight="1.0"/>
		</spawn>
	</room>
	<room variant="1" name="Ferrium - AT AN" type="1" subtype="2600" shape="1" width="13" height="7" difficulty="5" weight="0.0">
		<door exists="False" x="-1" y="3"/>
		<door exists="False" x="6" y="-1"/>
		<door exists="False" x="6" y="7"/>
		<door exists="False" x="13" y="3"/>
		<spawn x="0" y="0">
			<entity type="12005" variant="1" subtype="0" weight="1.0"/>
		</spawn>
		<spawn x="1" y="0">
			<entity type="12005" variant="1" subtype="1" weight="1.0"/>
		</spawn>
		<spawn x="2" y="0">
			<entity type="12005" variant="1" subtype="2" weight="1.0"/>
		</spawn>
		<spawn x="3" y="0">
			<entity type="12005" variant="1" subtype="3" weight="1.0"/>
		</spawn>
		<spawn x="4" y="0">
			<entity type="12005" variant="1" subtype="4" weight="1.0"/>
		</spawn>
		<spawn x="5" y="0">
			<entity type="12005" variant="1" subtype="5" weight="1.0"/>
		</spawn>
		<spawn x="6" y="0">
			<entity type="12006" variant="0" subtype="4" weight="1.0"/>
		</spawn>
		<spawn x="7" y="0">
			<entity type="12004" variant="133" subtype="326" weight="1.0"/>
		</spawn>
		<spawn x="8" y="0">
			<entity type="12004" variant="133" subtype="327" weight="1.0"/>
		</spawn>
		<spawn x="9" y="0">
			<entity type="12004" variant="133" subtype="328" weight="1.0"/>
		</spawn>
		<spawn x="10" y="0">
			<entity type="12004" variant="133" subtype="329" weight="1.0"/>
		</spawn>
		<spawn x="11" y="0">
			<entity type="12004" variant="133" subtype="330" weight="1.0"/>
		</spawn>
		<spawn x="12" y="0">
			<entity type="12004" variant="133" subtype="331" weight="1.0"/>
		</spawn>
		<spawn x="6" y="1">
			<entity type="12006" variant="0" subtype="4" weight="1.0"/>
		</spawn>
		<spawn x="0" y="2">
			<entity type="12006" variant="0" subtype="20" weight="1.0"/>
		</spawn>
		<spawn x="2" y="2">
			<entity type="12006" variant="0" subtype="20" weight="1.0"/>
		</spawn>
		<spawn x="3" y="2">
			<entity type="12006" variant="0" subtype="20" weight="1.0"/>
		</spawn>
		<spawn x="5" y="2">
			<entity type="12006" variant="0" subtype="20" weight="1.0"/>
		</spawn>
		<spawn x="6" y="2">
			<entity type="12006" variant="0" subtype="4" weight="1.0"/>
		</spawn>
		<spawn x="11" y="2">
			<entity type="12001" variant="0" subtype="0" weight="1.0"/>
		</spawn>
		<spawn x="6" y="3">
			<entity type="12006" variant="0" subtype="4" weight="1.0"/>
		</spawn>
		<spawn x="6" y="4">
			<entity type="12006" variant="0" subtype="4" weight="1.0"/>
		</spawn>
		<spawn x="7" y="4">
			<entity type="12006" variant="0" subtype="0" weight="1.0"/>
		</spawn>
		<spawn x="10" y="4">
			<entity type="12006" variant="0" subtype="0" weight="1.0"/>
		</spawn>
		<spawn x="11" y="4">
			<entity type="12006" variant="0" subtype="0" weight="1.0"/>
		</spawn>
		<spawn x="12" y="4">
			<entity type="12006" variant="0" subtype="0" weight="1.0"/>
		</spawn>
		<spawn x="3" y="5">
			<entity type="12000" variant="2602" subtype="20" weight="1.0"/>
		</spawn>
		<spawn x="6" y="5">
			<entity type="12006" variant="0" subtype="4" weight="1.0"/>
		</spawn>
		<spawn x="0" y="6">
			<entity type="12004" variant="133" subtype="320" weight="1.0"/>
		</spawn>
		<spawn x="1" y="6">
			<entity type="12004" variant="133" subtype="321" weight="1.0"/>
		</spawn>
		<spawn x="2" y="6">
			<entity type="12004" variant="133" subtype="322" weight="1.0"/>
		</spawn>
		<spawn x="3" y="6">
			<entity type="12004" variant="133" subtype="323" weight="1.0"/>
		</spawn>
		<spawn x="4" y="6">
			<entity type="12004" variant="133" subtype="324" weight="1.0"/>
		</spawn>
		<spawn x="5" y="6">
			<entity type="12004" variant="133" subtype="325" weight="1.0"/>
		</spawn>
		<spawn x="6" y="6">
			<entity type="12006" variant="0" subtype="4" weight="1.0"/>
		</spawn>
		<spawn x="7" y="6">
			<entity type="12005" variant="1" subtype="6" weight="1.0"/>
		</spawn>
		<spawn x="8" y="6">
			<entity type="12005" variant="1" subtype="7" weight="1.0"/>
		</spawn>
		<spawn x="9" y="6">
			<entity type="12005" variant="1" subtype="8" weight="1.0"/>
		</spawn>
		<spawn x="10" y="6">
			<entity type="12005" variant="1" subtype="9" weight="1.0"/>
		</spawn>
		<spawn x="11" y="6">
			<entity type="12005" variant="1" subtype="10" weight="1.0"/>
		</spawn>
		<spawn x="12" y="6">
			<entity type="12005" variant="1" subtype="11" weight="1.0"/>
		</spawn>
	</room>
	<room variant="2" name="Ferrium - EXHIBITION" type="1" subtype="2601" shape="1" width="13" height="7" difficulty="5" weight="0.0">
		<door exists="False" x="-1" y="3"/>
		<door exists="False" x="6" y="-1"/>
		<door exists="False" x="6" y="7"/>
		<door exists="False" x="13" y="3"/>
		<spawn x="0" y="0">
			<entity type="12005" variant="1" subtype="0" weight="1.0"/>
		</spawn>
		<spawn x="1" y="0">
			<entity type="12005" variant="1" subtype="1" weight="1.0"/>
		</spawn>
		<spawn x="2" y="0">
			<entity type="12005" variant="1" subtype="2" weight="1.0"/>
		</spawn>
		<spawn x="3" y="0">
			<entity type="12005" variant="1" subtype="3" weight="1.0"/>
		</spawn>
		<spawn x="4" y="0">
			<entity type="12005" variant="1" subtype="4" weight="1.0"/>
		</spawn>
		<spawn x="5" y="0">
			<entity type="12005" variant="1" subtype="5" weight="1.0"/>
		</spawn>
		<spawn x="6" y="0">
			<entity type="12006" variant="0" subtype="4" weight="1.0"/>
		</spawn>
		<spawn x="7" y="0">
			<entity type="12004" variant="133" subtype="326" weight="1.0"/>
		</spawn>
		<spawn x="8" y="0">
			<entity type="12004" variant="133" subtype="327" weight="1.0"/>
		</spawn>
		<spawn x="9" y="0">
			<entity type="12004" variant="133" subtype="328" weight="1.0"/>
		</spawn>
		<spawn x="10" y="0">
			<entity type="12004" variant="133" subtype="329" weight="1.0"/>
		</spawn>
		<spawn x="11" y="0">
			<entity type="12004" variant="133" subtype="330" weight="1.0"/>
		</spawn>
		<spawn x="12" y="0">
			<entity type="12004" variant="133" subtype="331" weight="1.0"/>
		</spawn>
		<spawn x="6" y="1">
			<entity type="12006" variant="0" subtype="4" weight="1.0"/>
		</spawn>
		<spawn x="9" y="1">
			<entity type="12000" variant="0" subtype="20" weight="1.0"/>
		</spawn>
		<spawn x="0" y="2">
			<entity type="12006" variant="0" subtype="0" weight="1.0"/>
		</spawn>
		<spawn x="2" y="2">
			<entity type="12006" variant="0" subtype="0" weight="1.0"/>
		</spawn>
		<spawn x="3" y="2">
			<entity type="12006" variant="0" subtype="0" weight="1.0"/>
		</spawn>
		<spawn x="5" y="2">
			<entity type="12006" variant="0" subtype="0" weight="1.0"/>
		</spawn>
		<spawn x="6" y="2">
			<entity type="12006" variant="0" subtype="4" weight="1.0"/>
		</spawn>
		<spawn x="7" y="2">
			<entity type="12006" variant="0" subtype="20" weight="1.0"/>
		</spawn>
		<spawn x="8" y="2">
			<entity type="12006" variant="0" subtype="20" weight="1.0"/>
		</spawn>
		<spawn x="9" y="2">
			<entity type="12006" variant="0" subtype="20" weight="1.0"/>
		</spawn>
		<spawn x="10" y="2">
			<entity type="12006" variant="0" subtype="20" weight="1.0"/>
		</spawn>
		<spawn x="11" y="2">
			<entity type="12006" variant="0" subtype="20" weight="1.0"/>
		</spawn>
		<spawn x="12" y="2">
			<entity type="12006" variant="0" subtype="20" weight="1.0"/>
		</spawn>
		<spawn x="6" y="3">
			<entity type="12006" variant="0" subtype="4" weight="1.0"/>
		</spawn>
		<spawn x="7" y="3">
			<entity type="12006" variant="0" subtype="20" weight="1.0"/>
		</spawn>
		<spawn x="8" y="3">
			<entity type="12006" variant="0" subtype="20" weight="1.0"/>
		</spawn>
		<spawn x="9" y="3">
			<entity type="12006" variant="0" subtype="20" weight="1.0"/>
		</spawn>
		<spawn x="10" y="3">
			<entity type="12006" variant="0" subtype="20" weight="1.0"/>
		</spawn>
		<spawn x="11" y="3">
			<entity type="12006" variant="0" subtype="20" weight="1.0"/>
		</spawn>
		<spawn x="12" y="3">
			<entity type="12006" variant="0" subtype="20" weight="1.0"/>
		</spawn>
		<spawn x="3" y="4">
			<entity type="12001" variant="0" subtype="0" weight="1.0"/>
		</spawn>
		<spawn x="6" y="4">
			<entity type="12006" variant="0" subtype="4" weight="1.0"/>
		</spawn>
		<spawn x="7" y="4">
			<entity type="12006" variant="0" subtype="20" weight="1.0"/>
		</spawn>
		<spawn x="8" y="4">
			<entity type="12006" variant="0" subtype="20" weight="1.0"/>
		</spawn>
		<spawn x="9" y="4">
			<entity type="12006" variant="0" subtype="20" weight="1.0"/>
		</spawn>
		<spawn x="10" y="4">
			<entity type="12006" variant="0" subtype="20" weight="1.0"/>
		</spawn>
		<spawn x="11" y="4">
			<entity type="12006" variant="0" subtype="20" weight="1.0"/>
		</spawn>
		<spawn x="12" y="4">
			<entity type="12006" variant="0" subtype="20" weight="1.0"/>
		</spawn>
		<spawn x="6" y="5">
			<entity type="12006" variant="0" subtype="4" weight="1.0"/>
		</spawn>
		<spawn x="7" y="5">
			<entity type="12006" variant="0" subtype="20" weight="1.0"/>
		</spawn>
		<spawn x="8" y="5">
			<entity type="12006" variant="0" subtype="20" weight="1.0"/>
		</spawn>
		<spawn x="9" y="5">
			<entity type="12006" variant="0" subtype="20" weight="1.0"/>
		</spawn>
		<spawn x="10" y="5">
			<entity type="12006" variant="0" subtype="20" weight="1.0"/>
		</spawn>
		<spawn x="11" y="5">
			<entity type="12006" variant="0" subtype="20" weight="1.0"/>
		</spawn>
		<spawn x="12" y="5">
			<entity type="12006" variant="0" subtype="20" weight="1.0"/>
		</spawn>
		<spawn x="0" y="6">
			<entity type="12004" variant="133" subtype="320" weight="1.0"/>
		</spawn>
		<spawn x="1" y="6">
			<entity type="12004" variant="133" subtype="321" weight="1.0"/>
		</spawn>
		<spawn x="2" y="6">
			<entity type="12004" variant="133" subtype="322" weight="1.0"/>
		</spawn>
		<spawn x="3" y="6">
			<entity type="12004" variant="133" subtype="323" weight="1.0"/>
		</spawn>
		<spawn x="4" y="6">
			<entity type="12004" variant="133" subtype="324" weight="1.0"/>
		</spawn>
		<spawn x="5" y="6">
			<entity type="12004" variant="133" subtype="325" weight="1.0"/>
		</spawn>
		<spawn x="6" y="6">
			<entity type="12006" variant="0" subtype="4" weight="1.0"/>
		</spawn>
		<spawn x="7" y="6">
			<entity type="12006" variant="0" subtype="20" weight="1.0"/>
			<entity type="12005" variant="1" subtype="6" weight="1.0"/>
		</spawn>
		<spawn x="8" y="6">
			<entity type="12006" variant="0" subtype="20" weight="1.0"/>
			<entity type="12005" variant="1" subtype="7" weight="1.0"/>
		</spawn>
		<spawn x="9" y="6">
			<entity type="12006" variant="0" subtype="20" weight="1.0"/>
			<entity type="12005" variant="1" subtype="8" weight="1.0"/>
		</spawn>
		<spawn x="10" y="6">
			<entity type="12006" variant="0" subtype="20" weight="1.0"/>
			<entity type="12005" variant="1" subtype="9" weight="1.0"/>
		</spawn>
		<spawn x="11" y="6">
			<entity type="12006" variant="0" subtype="20" weight="1.0"/>
			<entity type="12005" variant="1" subtype="10" weight="1.0"/>
		</spawn>
		<spawn x="12" y="6">
			<entity type="12006" variant="0" subtype="20" weight="1.0"/>
			<entity type="12005" variant="1" subtype="11" weight="1.0"/>
		</spawn>
	</room>
	<room variant="3" name="Ferrium - CONVERGENCE" type="1" subtype="0" shape="1" width="13" height="7" difficulty="10" weight="1.0">
		<door exists="False" x="-1" y="3"/>
		<door exists="False" x="6" y="-1"/>
		<door exists="False" x="6" y="7"/>
		<door exists="False" x="13" y="3"/>
		<spawn x="13" y="-1">
			<entity type="12005" variant="1" subtype="7" weight="1.0"/>
		</spawn>
		<spawn x="-1" y="0">
			<entity type="12005" variant="1" subtype="8" weight="1.0"/>
		</spawn>
		<spawn x="3" y="0">
			<entity type="12006" variant="0" subtype="0" weight="1.0"/>
		</spawn>
		<spawn x="4" y="0">
			<entity type="12006" variant="0" subtype="278" weight="1.0"/>
		</spawn>
		<spawn x="5" y="0">
			<entity type="12006" variant="0" subtype="278" weight="1.0"/>
		</spawn>
		<spawn x="6" y="0">
			<entity type="12006" variant="0" subtype="278" weight="1.0"/>
		</spawn>
		<spawn x="7" y="0">
			<entity type="12006" variant="0" subtype="278" weight="1.0"/>
		</spawn>
		<spawn x="11" y="0">
			<entity type="12006" variant="0" subtype="0" weight="1.0"/>
		</spawn>
		<spawn x="12" y="0">
			<entity type="12004" variant="895" subtype="456" weight="1.0"/>
			<entity type="12008" variant="1" subtype="31248" weight="1.0"/>
		</spawn>
		<spawn x="13" y="0">
			<entity type="12005" variant="1" subtype="6" weight="1.0"/>
		</spawn>
		<spawn x="-1" y="1">
			<entity type="12005" variant="1" subtype="9" weight="1.0"/>
		</spawn>
		<spawn x="1" y="1">
			<entity type="199" variant="20" subtype="0" weight="1.0"/>
			<entity type="12000" variant="0" subtype="535" weight="1.0"/>
		</spawn>
		<spawn x="3" y="1">
			<entity type="12006" variant="0" subtype="0" weight="1.0"/>
		</spawn>
		<spawn x="4" y="1">
			<entity type="12006" variant="0" subtype="278" weight="1.0"/>
		</spawn>
		<spawn x="5" y="1">
			<entity type="12006" variant="0" subtype="278" weight="1.0"/>
		</spawn>
		<spawn x="6" y="1">
			<entity type="12006" variant="0" subtype="278" weight="1.0"/>
		</spawn>
		<spawn x="12" y="1">
			<entity type="12006" variant="0" subtype="0" weight="1.0"/>
		</spawn>
		<spawn x="13" y="1">
			<entity type="12005" variant="1" subtype="5" weight="1.0"/>
		</spawn>
		<spawn x="-1" y="2">
			<entity type="12005" variant="1" subtype="10" weight="1.0"/>
		</spawn>
		<spawn x="0" y="2">
			<entity type="12006" variant="0" subtype="0" weight="1.0"/>
		</spawn>
		<spawn x="1" y="2">
			<entity type="12006" variant="0" subtype="0" weight="1.0"/>
		</spawn>
		<spawn x="2" y="2">
			<entity type="12006" variant="0" subtype="0" weight="1.0"/>
		</spawn>
		<spawn x="13" y="2">
			<entity type="12005" variant="1" subtype="4" weight="1.0"/>
		</spawn>
		<spawn x="-1" y="3">
			<entity type="12005" variant="1" subtype="11" weight="1.0"/>
		</spawn>
		<spawn x="0" y="3">
			<entity type="12006" variant="0" subtype="0" weight="1.0"/>
		</spawn>
		<spawn x="1" y="3">
			<entity type="12006" variant="0" subtype="0" weight="1.0"/>
		</spawn>
		<spawn x="6" y="3">
			<entity type="12001" variant="0" subtype="0" weight="1.0"/>
		</spawn>
		<spawn x="11" y="3">
			<entity type="12006" variant="0" subtype="0" weight="1.0"/>
		</spawn>
		<spawn x="12" y="3">
			<entity type="12006" variant="0" subtype="0" weight="1.0"/>
		</spawn>
		<spawn x="13" y="3">
			<entity type="12005" variant="1" subtype="3" weight="1.0"/>
		</spawn>
		<spawn x="-1" y="4">
			<entity type="12005" variant="1" subtype="12" weight="1.0"/>
		</spawn>
		<spawn x="10" y="4">
			<entity type="12006" variant="0" subtype="0" weight="1.0"/>
		</spawn>
		<spawn x="11" y="4">
			<entity type="12006" variant="0" subtype="0" weight="1.0"/>
		</spawn>
		<spawn x="12" y="4">
			<entity type="12006" variant="0" subtype="0" weight="1.0"/>
		</spawn>
		<spawn x="13" y="4">
			<entity type="12005" variant="1" subtype="2" weight="1.0"/>
		</spawn>
		<spawn x="-1" y="5">
			<entity type="12005" variant="1" subtype="13" weight="1.0"/>
		</spawn>
		<spawn x="0" y="5">
			<entity type="12006" variant="0" subtype="0" weight="1.0"/>
		</spawn>
		<spawn x="6" y="5">
			<entity type="12006" variant="0" subtype="278" weight="1.0"/>
		</spawn>
		<spawn x="7" y="5">
			<entity type="12006" variant="0" subtype="278" weight="1.0"/>
		</spawn>
		<spawn x="8" y="5">
			<entity type="12006" variant="0" subtype="278" weight="1.0"/>
		</spawn>
		<spawn x="9" y="5">
			<entity type="12006" variant="0" subtype="0" weight="1.0"/>
		</spawn>
		<spawn x="13" y="5">
			<entity type="12005" variant="1" subtype="1" weight="1.0"/>
		</spawn>
		<spawn x="-1" y="6">
			<entity type="12005" variant="1" subtype="14" weight="1.0"/>
		</spawn>
		<spawn x="0" y="6">
			<entity type="12004" variant="895" subtype="448" weight="1.0"/>
			<entity type="12008" variant="1" subtype="14352" weight="1.0"/>
		</spawn>
		<spawn x="1" y="6">
			<entity type="12006" variant="0" subtype="0" weight="1.0"/>
		</spawn>
		<spawn x="5" y="6">
			<entity type="12006" variant="0" subtype="278" weight="1.0"/>
		</spawn>
		<spawn x="6" y="6">
			<entity type="12006" variant="0" subtype="278" weight="1.0"/>
		</spawn>
		<spawn x="7" y="6">
			<entity type="12006" variant="0" subtype="278" weight="1.0"/>
		</spawn>
		<spawn x="8" y="6">
			<entity type="12006" variant="0" subtype="278" weight="1.0"/>
		</spawn>
		<spawn x="9" y="6">
			<entity type="12006" variant="0" subtype="0" weight="1.0"/>
		</spawn>
		<spawn x="11" y="6">
			<entity type="199" variant="20" subtype="0" weight="1.0"/>
		</spawn>
		<spawn x="13" y="6">
			<entity type="12005" variant="1" subtype="0" weight="1.0"/>
		</spawn>
		<spawn x="-1" y="7">
			<entity type="12005" variant="1" subtype="15" weight="1.0"/>
		</spawn>
	</room>
	<room variant="4" name="Ferrium - NOTES FROM A CITY UNKNOWN" type="1" subtype="0" shape="1" width="13" height="7" difficulty="1" weight="1.0">
		<door exists="False" x="-1" y="3"/>
		<door exists="False" x="6" y="-1"/>
		<door exists="False" x="6" y="7"/>
		<door exists="False" x="13" y="3"/>
		<spawn x="0" y="0">
			<entity type="12006" variant="0" subtype="0" weight="1.0"/>
		</spawn>
		<spawn x="2" y="0">
			<entity type="12006" variant="0" subtype="0" weight="1.0"/>
		</spawn>
		<spawn x="3" y="0">
			<entity type="12006" variant="0" subtype="19" weight="1.0"/>
		</spawn>
		<spawn x="4" y="0">
			<entity type="12006" variant="0" subtype="19" weight="1.0"/>
		</spawn>
		<spawn x="8" y="0">
			<entity type="12006" variant="0" subtype="19" weight="1.0"/>
		</spawn>
		<spawn x="9" y="0">
			<entity type="12006" variant="0" subtype="19" weight="1.0"/>
		</spawn>
		<spawn x="10" y="0">
			<entity type="12006" variant="0" subtype="0" weight="1.0"/>
		</spawn>
		<spawn x="12" y="0">
			<entity type="12006" variant="0" subtype="0" weight="1.0"/>
		</spawn>
		<spawn x="3" y="1">
			<entity type="12006" variant="0" subtype="19" weight="1.0"/>
		</spawn>
		<spawn x="9" y="1">
			<entity type="12006" variant="0" subtype="19" weight="1.0"/>
		</spawn>
		<spawn x="3" y="2">
			<entity type="12006" variant="0" subtype="19" weight="1.0"/>
		</spawn>
		<spawn x="4" y="2">
			<entity type="12006" variant="0" subtype="19" weight="1.0"/>
		</spawn>
		<spawn x="6" y="2">
			<entity type="12000" variant="0" subtype="20" weight="1.0"/>
		</spawn>
		<spawn x="8" y="2">
			<entity type="12006" variant="0" subtype="19" weight="1.0"/>
		</spawn>
		<spawn x="9" y="2">
			<entity type="12006" variant="0" subtype="19" weight="1.0"/>
		</spawn>
		<spawn x="3" y="3">
			<entity type="12006" variant="0" subtype="0" weight="1.0"/>
		</spawn>
		<spawn x="4" y="3">
			<entity type="12006" variant="0" subtype="19" weight="1.0"/>
		</spawn>
		<spawn x="5" y="3">
			<entity type="12006" variant="0" subtype="19" weight="1.0"/>
		</spawn>
		<spawn x="6" y="3">
			<entity type="12006" variant="0" subtype="19" weight="1.0"/>
		</spawn>
		<spawn x="7" y="3">
			<entity type="12006" variant="0" subtype="19" weight="1.0"/>
		</spawn>
		<spawn x="8" y="3">
			<entity type="12006" variant="0" subtype="19" weight="1.0"/>
		</spawn>
		<spawn x="9" y="3">
			<entity type="12006" variant="0" subtype="0" weight="1.0"/>
		</spawn>
		<spawn x="3" y="4">
			<entity type="12006" variant="0" subtype="0" weight="1.0"/>
		</spawn>
		<spawn x="4" y="4">
			<entity type="12006" variant="0" subtype="0" weight="1.0"/>
		</spawn>
		<spawn x="5" y="4">
			<entity type="12006" variant="0" subtype="0" weight="1.0"/>
		</spawn>
		<spawn x="6" y="4">
			<entity type="12006" variant="0" subtype="0" weight="1.0"/>
		</spawn>
		<spawn x="7" y="4">
			<entity type="12006" variant="0" subtype="0" weight="1.0"/>
		</spawn>
		<spawn x="8" y="4">
			<entity type="12006" variant="0" subtype="0" weight="1.0"/>
		</spawn>
		<spawn x="9" y="4">
			<entity type="12006" variant="0" subtype="0" weight="1.0"/>
		</spawn>
		<spawn x="1" y="5">
			<entity type="12001" variant="0" subtype="0" weight="1.0"/>
			<entity type="199" variant="20" subtype="0" weight="1.0"/>
		</spawn>
		<spawn x="4" y="5">
			<entity type="12006" variant="0" subtype="0" weight="1.0"/>
		</spawn>
		<spawn x="5" y="5">
			<entity type="12006" variant="0" subtype="0" weight="1.0"/>
		</spawn>
		<spawn x="6" y="5">
			<entity type="12006" variant="0" subtype="0" weight="1.0"/>
		</spawn>
		<spawn x="7" y="5">
			<entity type="12006" variant="0" subtype="0" weight="1.0"/>
		</spawn>
		<spawn x="8" y="5">
			<entity type="12006" variant="0" subtype="0" weight="1.0"/>
		</spawn>
		<spawn x="11" y="5">
			<entity type="199" variant="20" subtype="0" weight="1.0"/>
		</spawn>
		<spawn x="4" y="6">
			<entity type="12006" variant="0" subtype="0" weight="1.0"/>
		</spawn>
		<spawn x="5" y="6">
			<entity type="12006" variant="0" subtype="0" weight="1.0"/>
		</spawn>
		<spawn x="6" y="6">
			<entity type="12006" variant="0" subtype="0" weight="1.0"/>
		</spawn>
		<spawn x="7" y="6">
			<entity type="12006" variant="0" subtype="0" weight="1.0"/>
		</spawn>
		<spawn x="8" y="6">
			<entity type="12006" variant="0" subtype="0" weight="1.0"/>
		</spawn>
	</room>
	<room variant="5" name="Ferrium - TREAD LIGHTLY" type="1" subtype="0" shape="1" width="13" height="7" difficulty="10" weight="1.0">
		<door exists="False" x="-1" y="3"/>
		<door exists="False" x="6" y="-1"/>
		<door exists="False" x="6" y="7"/>
		<door exists="False" x="13" y="3"/>
		<spawn x="0" y="-1">
			<entity type="12005" variant="1" subtype="0" weight="1.0"/>
		</spawn>
		<spawn x="12" y="-1">
			<entity type="12005" variant="1" subtype="1" weight="1.0"/>
		</spawn>
		<spawn x="0" y="0">
			<entity type="12006" variant="0" subtype="0" weight="1.0"/>
		</spawn>
		<spawn x="1" y="0">
			<entity type="12006" variant="0" subtype="0" weight="1.0"/>
		</spawn>
		<spawn x="2" y="0">
			<entity type="12006" variant="0" subtype="0" weight="1.0"/>
		</spawn>
		<spawn x="3" y="0">
			<entity type="12004" variant="1407" subtype="9152" weight="1.0"/>
			<entity type="12008" variant="1" subtype="15" weight="1.0"/>
		</spawn>
		<spawn x="4" y="0">
			<entity type="12006" variant="0" subtype="0" weight="1.0"/>
		</spawn>
		<spawn x="8" y="0">
			<entity type="12006" variant="0" subtype="0" weight="1.0"/>
		</spawn>
		<spawn x="9" y="0">
			<entity type="12004" variant="1407" subtype="9153" weight="1.0"/>
			<entity type="12008" variant="1" subtype="1" weight="1.0"/>
		</spawn>
		<spawn x="10" y="0">
			<entity type="12006" variant="0" subtype="0" weight="1.0"/>
		</spawn>
		<spawn x="11" y="0">
			<entity type="12006" variant="0" subtype="0" weight="1.0"/>
		</spawn>
		<spawn x="12" y="0">
			<entity type="12006" variant="0" subtype="0" weight="1.0"/>
		</spawn>
		<spawn x="0" y="1">
			<entity type="12006" variant="0" subtype="36" weight="1.0"/>
		</spawn>
		<spawn x="1" y="1">
			<entity type="12006" variant="0" subtype="0" weight="1.0"/>
		</spawn>
		<spawn x="2" y="1">
			<entity type="12006" variant="0" subtype="182" weight="1.0"/>
		</spawn>
		<spawn x="3" y="1">
			<entity type="12006" variant="0" subtype="182" weight="1.0"/>
		</spawn>
		<spawn x="4" y="1">
			<entity type="12003" variant="895" subtype="24621" weight="1.0"/>
		</spawn>
		<spawn x="8" y="1">
			<entity type="12003" variant="895" subtype="24621" weight="1.0"/>
		</spawn>
		<spawn x="9" y="1">
			<entity type="12006" variant="0" subtype="182" weight="1.0"/>
		</spawn>
		<spawn x="10" y="1">
			<entity type="12006" variant="0" subtype="182" weight="1.0"/>
		</spawn>
		<spawn x="11" y="1">
			<entity type="12006" variant="0" subtype="0" weight="1.0"/>
		</spawn>
		<spawn x="12" y="1">
			<entity type="12006" variant="0" subtype="0" weight="1.0"/>
		</spawn>
		<spawn x="0" y="2">
			<entity type="12006" variant="0" subtype="182" weight="1.0"/>
		</spawn>
		<spawn x="1" y="2">
			<entity type="12006" variant="0" subtype="182" weight="1.0"/>
		</spawn>
		<spawn x="2" y="2">
			<entity type="12006" variant="0" subtype="182" weight="1.0"/>
		</spawn>
		<spawn x="3" y="2">
			<entity type="12006" variant="0" subtype="182" weight="1.0"/>
		</spawn>
		<spawn x="4" y="2">
			<entity type="12006" variant="0" subtype="182" weight="1.0"/>
		</spawn>
		<spawn x="6" y="2">
			<entity type="12000" variant="0" subtype="1310" weight="1.0"/>
		</spawn>
		<spawn x="8" y="2">
			<entity type="12006" variant="0" subtype="182" weight="1.0"/>
		</spawn>
		<spawn x="9" y="2">
			<entity type="12006" variant="0" subtype="182" weight="1.0"/>
		</spawn>
		<spawn x="10" y="2">
			<entity type="12006" variant="0" subtype="182" weight="1.0"/>
		</spawn>
		<spawn x="11" y="2">
			<entity type="12006" variant="0" subtype="182" weight="1.0"/>
		</spawn>
		<spawn x="12" y="2">
			<entity type="12006" variant="0" subtype="182" weight="1.0"/>
		</spawn>
		<spawn x="0" y="3">
			<entity type="12006" variant="0" subtype="182" weight="1.0"/>
		</spawn>
		<spawn x="1" y="3">
			<entity type="12006" variant="0" subtype="182" weight="1.0"/>
		</spawn>
		<spawn x="5" y="3">
			<entity type="12006" variant="0" subtype="0" weight="1.0"/>
		</spawn>
		<spawn x="6" y="3">
			<entity type="12006" variant="0" subtype="0" weight="1.0"/>
		</spawn>
		<spawn x="7" y="3">
			<entity type="12006" variant="0" subtype="0" weight="1.0"/>
		</spawn>
		<spawn x="11" y="3">
			<entity type="12006" variant="0" subtype="182" weight="1.0"/>
		</spawn>
		<spawn x="12" y="3">
			<entity type="12006" variant="0" subtype="182" weight="1.0"/>
		</spawn>
		<spawn x="0" y="4">
			<entity type="12006" variant="0" subtype="182" weight="1.0"/>
		</spawn>
		<spawn x="3" y="4">
			<entity type="12001" variant="0" subtype="0" weight="1.0"/>
			<entity type="199" variant="20" subtype="0" weight="1.0"/>
		</spawn>
		<spawn x="9" y="4">
			<entity type="199" variant="20" subtype="0" weight="1.0"/>
		</spawn>
		<spawn x="12" y="4">
			<entity type="12006" variant="0" subtype="182" weight="1.0"/>
		</spawn>
		<spawn x="0" y="5">
			<entity type="12006" variant="0" subtype="182" weight="1.0"/>
		</spawn>
		<spawn x="6" y="5">
			<entity type="12005" variant="1" subtype="2" weight="1.0"/>
		</spawn>
		<spawn x="12" y="5">
			<entity type="12006" variant="0" subtype="182" weight="1.0"/>
		</spawn>
		<spawn x="0" y="6">
			<entity type="12006" variant="0" subtype="182" weight="1.0"/>
		</spawn>
		<spawn x="1" y="6">
			<entity type="12006" variant="0" subtype="182" weight="1.0"/>
		</spawn>
		<spawn x="11" y="6">
			<entity type="12006" variant="0" subtype="182" weight="1.0"/>
		</spawn>
		<spawn x="12" y="6">
			<entity type="12006" variant="0" subtype="182" weight="1.0"/>
		</spawn>
	</room>
	<room variant="6" name="Ferrium - CREEPING" type="1" subtype="0" shape="1" width="13" height="7" difficulty="10" weight="1.0">
		<door exists="False" x="-1" y="3"/>
		<door exists="False" x="6" y="-1"/>
		<door exists="False" x="6" y="7"/>
		<door exists="False" x="13" y="3"/>
		<spawn x="9" y="0">
			<entity type="12006" variant="0" subtype="48" weight="1.0"/>
		</spawn>
		<spawn x="10" y="0">
			<entity type="12006" variant="0" subtype="0" weight="1.0"/>
		</spawn>
		<spawn x="11" y="0">
			<entity type="12006" variant="0" subtype="0" weight="1.0"/>
		</spawn>
		<spawn x="12" y="0">
			<entity type="12006" variant="0" subtype="0" weight="1.0"/>
		</spawn>
		<spawn x="9" y="1">
			<entity type="12006" variant="0" subtype="48" weight="1.0"/>
		</spawn>
		<spawn x="10" y="1">
			<entity type="12002" variant="127" subtype="4083" weight="1.0"/>
		</spawn>
		<spawn x="11" y="1">
			<entity type="12006" variant="0" subtype="0" weight="1.0"/>
		</spawn>
		<spawn x="12" y="1">
			<entity type="12006" variant="0" subtype="0" weight="1.0"/>
		</spawn>
		<spawn x="9" y="2">
			<entity type="12006" variant="0" subtype="48" weight="1.0"/>
		</spawn>
		<spawn x="1" y="3">
			<entity type="12001" variant="0" subtype="0" weight="1.0"/>
		</spawn>
		<spawn x="9" y="3">
			<entity type="12006" variant="0" subtype="48" weight="1.0"/>
		</spawn>
		<spawn x="11" y="3">
			<entity type="12000" variant="2603" subtype="10" weight="1.0"/>
		</spawn>
		<spawn x="9" y="4">
			<entity type="12006" variant="0" subtype="48" weight="1.0"/>
		</spawn>
		<spawn x="10" y="4">
			<entity type="12006" variant="0" subtype="0" weight="1.0"/>
		</spawn>
		<spawn x="11" y="4">
			<entity type="12006" variant="0" subtype="0" weight="1.0"/>
		</spawn>
		<spawn x="12" y="4">
			<entity type="12006" variant="0" subtype="0" weight="1.0"/>
		</spawn>
		<spawn x="9" y="5">
			<entity type="12006" variant="0" subtype="48" weight="1.0"/>
		</spawn>
		<spawn x="10" y="5">
			<entity type="12002" variant="127" subtype="499" weight="1.0"/>
		</spawn>
		<spawn x="11" y="5">
			<entity type="12006" variant="0" subtype="0" weight="1.0"/>
		</spawn>
		<spawn x="12" y="5">
			<entity type="12006" variant="0" subtype="0" weight="1.0"/>
		</spawn>
		<spawn x="9" y="6">
			<entity type="12006" variant="0" subtype="48" weight="1.0"/>
		</spawn>
		<spawn x="10" y="6">
			<entity type="12006" variant="0" subtype="0" weight="1.0"/>
		</spawn>
		<spawn x="11" y="6">
			<entity type="12006" variant="0" subtype="0" weight="1.0"/>
		</spawn>
		<spawn x="12" y="6">
			<entity type="12006" variant="0" subtype="0" weight="1.0"/>
		</spawn>
	</room>
	<room variant="7" name="Ferrium - EVER" type="1" subtype="2602" shape="1" width="13" height="7" difficulty="10" weight="1.0">
		<door exists="False" x="-1" y="3"/>
		<door exists="False" x="6" y="-1"/>
		<door exists="False" x="6" y="7"/>
		<door exists="False" x="13" y="3"/>
		<spawn x="6" y="0">
			<entity type="12006" variant="0" subtype="48" weight="1.0"/>
		</spawn>
		<spawn x="7" y="0">
			<entity type="12006" variant="0" subtype="0" weight="1.0"/>
		</spawn>
		<spawn x="8" y="0">
			<entity type="12006" variant="0" subtype="0" weight="1.0"/>
		</spawn>
		<spawn x="9" y="0">
			<entity type="12006" variant="0" subtype="0" weight="1.0"/>
		</spawn>
		<spawn x="10" y="0">
			<entity type="12006" variant="0" subtype="0" weight="1.0"/>
		</spawn>
		<spawn x="11" y="0">
			<entity type="12006" variant="0" subtype="0" weight="1.0"/>
		</spawn>
		<spawn x="12" y="0">
			<entity type="12006" variant="0" subtype="0" weight="1.0"/>
		</spawn>
		<spawn x="6" y="1">
			<entity type="12006" variant="0" subtype="48" weight="1.0"/>
		</spawn>
		<spawn x="10" y="1">
			<entity type="12002" variant="127" subtype="4083" weight="1.0"/>
		</spawn>
		<spawn x="11" y="1">
			<entity type="12006" variant="0" subtype="0" weight="1.0"/>
		</spawn>
		<spawn x="12" y="1">
			<entity type="12006" variant="0" subtype="0" weight="1.0"/>
		</spawn>
		<spawn x="6" y="2">
			<entity type="12006" variant="0" subtype="48" weight="1.0"/>
		</spawn>
		<spawn x="8" y="2">
			<entity type="12000" variant="2604" subtype="10" weight="1.0"/>
		</spawn>
		<spawn x="10" y="2">
			<entity type="12006" variant="0" subtype="0" weight="1.0"/>
		</spawn>
		<spawn x="11" y="2">
			<entity type="12006" variant="0" subtype="0" weight="1.0"/>
		</spawn>
		<spawn x="12" y="2">
			<entity type="12006" variant="0" subtype="0" weight="1.0"/>
		</spawn>
		<spawn x="1" y="3">
			<entity type="12001" variant="0" subtype="0" weight="1.0"/>
		</spawn>
		<spawn x="5" y="3">
			<entity type="12007" variant="0" subtype="117" weight="1.0"/>
		</spawn>
		<spawn x="6" y="3">
			<entity type="12006" variant="0" subtype="48" weight="1.0"/>
		</spawn>
		<spawn x="7" y="3">
			<entity type="12006" variant="0" subtype="0" weight="1.0"/>
		</spawn>
		<spawn x="8" y="3">
			<entity type="12006" variant="0" subtype="0" weight="1.0"/>
		</spawn>
		<spawn x="9" y="3">
			<entity type="12006" variant="0" subtype="0" weight="1.0"/>
		</spawn>
		<spawn x="10" y="3">
			<entity type="12006" variant="0" subtype="0" weight="1.0"/>
		</spawn>
		<spawn x="11" y="3">
			<entity type="12006" variant="0" subtype="0" weight="1.0"/>
		</spawn>
		<spawn x="12" y="3">
			<entity type="12006" variant="0" subtype="0" weight="1.0"/>
		</spawn>
		<spawn x="6" y="4">
			<entity type="12006" variant="0" subtype="48" weight="1.0"/>
		</spawn>
		<spawn x="7" y="4">
			<entity type="12002" variant="137" subtype="3299" weight="1.0"/>
		</spawn>
		<spawn x="8" y="4">
			<entity type="12006" variant="0" subtype="0" weight="1.0"/>
		</spawn>
		<spawn x="9" y="4">
			<entity type="12006" variant="0" subtype="0" weight="1.0"/>
		</spawn>
		<spawn x="10" y="4">
			<entity type="12006" variant="0" subtype="0" weight="1.0"/>
		</spawn>
		<spawn x="11" y="4">
			<entity type="12006" variant="0" subtype="0" weight="1.0"/>
		</spawn>
		<spawn x="12" y="4">
			<entity type="12006" variant="0" subtype="0" weight="1.0"/>
		</spawn>
		<spawn x="6" y="5">
			<entity type="12006" variant="0" subtype="48" weight="1.0"/>
		</spawn>
		<spawn x="7" y="5">
			<entity type="12006" variant="0" subtype="0" weight="1.0"/>
		</spawn>
		<spawn x="8" y="5">
			<entity type="12006" variant="0" subtype="0" weight="1.0"/>
		</spawn>
		<spawn x="9" y="5">
			<entity type="12006" variant="0" subtype="0" weight="1.0"/>
		</spawn>
		<spawn x="10" y="5">
			<entity type="12002" variant="127" subtype="497" weight="1.0"/>
		</spawn>
		<spawn x="11" y="5">
			<entity type="12006" variant="0" subtype="0" weight="1.0"/>
		</spawn>
		<spawn x="12" y="5">
			<entity type="12006" variant="0" subtype="0" weight="1.0"/>
		</spawn>
		<spawn x="6" y="6">
			<entity type="12006" variant="0" subtype="48" weight="1.0"/>
		</spawn>
		<spawn x="7" y="6">
			<entity type="12002" variant="137" subtype="1251" weight="1.0"/>
		</spawn>
		<spawn x="8" y="6">
			<entity type="12006" variant="0" subtype="0" weight="1.0"/>
		</spawn>
		<spawn x="9" y="6">
			<entity type="12006" variant="0" subtype="0" weight="1.0"/>
		</spawn>
		<spawn x="10" y="6">
			<entity type="12006" variant="0" subtype="0" weight="1.0"/>
		</spawn>
		<spawn x="11" y="6">
			<entity type="12006" variant="0" subtype="0" weight="1.0"/>
		</spawn>
		<spawn x="12" y="6">
			<entity type="12006" variant="0" subtype="0" weight="1.0"/>
		</spawn>
	</room>
	<room variant="8" name="Ferrium - CLOSER" type="1" subtype="2603" shape="1" width="13" height="7" difficulty="10" weight="1.0">
		<door exists="False" x="-1" y="3"/>
		<door exists="False" x="6" y="-1"/>
		<door exists="False" x="6" y="7"/>
		<door exists="False" x="13" y="3"/>
		<spawn x="3" y="0">
			<entity type="12006" variant="0" subtype="48" weight="1.0"/>
		</spawn>
		<spawn x="4" y="0">
			<entity type="12006" variant="0" subtype="0" weight="1.0"/>
		</spawn>
		<spawn x="5" y="0">
			<entity type="12006" variant="0" subtype="0" weight="1.0"/>
		</spawn>
		<spawn x="6" y="0">
			<entity type="12006" variant="0" subtype="0" weight="1.0"/>
		</spawn>
		<spawn x="7" y="0">
			<entity type="12006" variant="0" subtype="0" weight="1.0"/>
		</spawn>
		<spawn x="8" y="0">
			<entity type="12006" variant="0" subtype="0" weight="1.0"/>
		</spawn>
		<spawn x="9" y="0">
			<entity type="12006" variant="0" subtype="0" weight="1.0"/>
		</spawn>
		<spawn x="10" y="0">
			<entity type="12006" variant="0" subtype="0" weight="1.0"/>
		</spawn>
		<spawn x="11" y="0">
			<entity type="12006" variant="0" subtype="0" weight="1.0"/>
		</spawn>
		<spawn x="12" y="0">
			<entity type="12006" variant="0" subtype="0" weight="1.0"/>
		</spawn>
		<spawn x="3" y="1">
			<entity type="12006" variant="0" subtype="48" weight="1.0"/>
		</spawn>
		<spawn x="4" y="1">
			<entity type="12006" variant="0" subtype="0" weight="1.0"/>
		</spawn>
		<spawn x="5" y="1">
			<entity type="12006" variant="0" subtype="0" weight="1.0"/>
		</spawn>
		<spawn x="6" y="1">
			<entity type="12006" variant="0" subtype="0" weight="1.0"/>
		</spawn>
		<spawn x="7" y="1">
			<entity type="12006" variant="0" subtype="0" weight="1.0"/>
		</spawn>
		<spawn x="8" y="1">
			<entity type="12006" variant="0" subtype="0" weight="1.0"/>
		</spawn>
		<spawn x="9" y="1">
			<entity type="12006" variant="0" subtype="0" weight="1.0"/>
		</spawn>
		<spawn x="10" y="1">
			<entity type="12002" variant="127" subtype="4083" weight="1.0"/>
		</spawn>
		<spawn x="11" y="1">
			<entity type="12006" variant="0" subtype="0" weight="1.0"/>
		</spawn>
		<spawn x="12" y="1">
			<entity type="12006" variant="0" subtype="0" weight="1.0"/>
		</spawn>
		<spawn x="3" y="2">
			<entity type="12006" variant="0" subtype="48" weight="1.0"/>
		</spawn>
		<spawn x="4" y="2">
			<entity type="12002" variant="137" subtype="211" weight="1.0"/>
		</spawn>
		<spawn x="5" y="2">
			<entity type="12006" variant="0" subtype="0" weight="1.0"/>
		</spawn>
		<spawn x="6" y="2">
			<entity type="12006" variant="0" subtype="0" weight="1.0"/>
		</spawn>
		<spawn x="7" y="2">
			<entity type="12006" variant="0" subtype="0" weight="1.0"/>
		</spawn>
		<spawn x="8" y="2">
			<entity type="12006" variant="0" subtype="0" weight="1.0"/>
		</spawn>
		<spawn x="9" y="2">
			<entity type="12006" variant="0" subtype="0" weight="1.0"/>
		</spawn>
		<spawn x="10" y="2">
			<entity type="12006" variant="0" subtype="0" weight="1.0"/>
		</spawn>
		<spawn x="11" y="2">
			<entity type="12006" variant="0" subtype="0" weight="1.0"/>
		</spawn>
		<spawn x="12" y="2">
			<entity type="12006" variant="0" subtype="0" weight="1.0"/>
		</spawn>
		<spawn x="0" y="3">
			<entity type="12007" variant="0" subtype="107" weight="1.0"/>
		</spawn>
		<spawn x="1" y="3">
			<entity type="12001" variant="0" subtype="0" weight="1.0"/>
		</spawn>
		<spawn x="3" y="3">
			<entity type="12006" variant="0" subtype="48" weight="1.0"/>
		</spawn>
		<spawn x="4" y="3">
			<entity type="12006" variant="0" subtype="0" weight="1.0"/>
		</spawn>
		<spawn x="5" y="3">
			<entity type="12006" variant="0" subtype="0" weight="1.0"/>
		</spawn>
		<spawn x="6" y="3">
			<entity type="12006" variant="0" subtype="0" weight="1.0"/>
		</spawn>
		<spawn x="7" y="3">
			<entity type="12006" variant="0" subtype="0" weight="1.0"/>
		</spawn>
		<spawn x="8" y="3">
			<entity type="12006" variant="0" subtype="0" weight="1.0"/>
		</spawn>
		<spawn x="9" y="3">
			<entity type="12006" variant="0" subtype="0" weight="1.0"/>
		</spawn>
		<spawn x="10" y="3">
			<entity type="12006" variant="0" subtype="0" weight="1.0"/>
		</spawn>
		<spawn x="11" y="3">
			<entity type="12006" variant="0" subtype="0" weight="1.0"/>
		</spawn>
		<spawn x="12" y="3">
			<entity type="12006" variant="0" subtype="0" weight="1.0"/>
		</spawn>
		<spawn x="3" y="4">
			<entity type="12006" variant="0" subtype="48" weight="1.0"/>
		</spawn>
		<spawn x="7" y="4">
			<entity type="12002" variant="137" subtype="3299" weight="1.0"/>
		</spawn>
		<spawn x="8" y="4">
			<entity type="12006" variant="0" subtype="0" weight="1.0"/>
		</spawn>
		<spawn x="9" y="4">
			<entity type="12006" variant="0" subtype="0" weight="1.0"/>
		</spawn>
		<spawn x="10" y="4">
			<entity type="12006" variant="0" subtype="0" weight="1.0"/>
		</spawn>
		<spawn x="11" y="4">
			<entity type="12006" variant="0" subtype="0" weight="1.0"/>
		</spawn>
		<spawn x="12" y="4">
			<entity type="12006" variant="0" subtype="0" weight="1.0"/>
		</spawn>
		<spawn x="3" y="5">
			<entity type="12006" variant="0" subtype="48" weight="1.0"/>
		</spawn>
		<spawn x="5" y="5">
			<entity type="12000" variant="0" subtype="25" weight="1.0"/>
		</spawn>
		<spawn x="7" y="5">
			<entity type="12006" variant="0" subtype="0" weight="1.0"/>
		</spawn>
		<spawn x="8" y="5">
			<entity type="12006" variant="0" subtype="0" weight="1.0"/>
		</spawn>
		<spawn x="9" y="5">
			<entity type="12006" variant="0" subtype="0" weight="1.0"/>
		</spawn>
		<spawn x="10" y="5">
			<entity type="12002" variant="127" subtype="497" weight="1.0"/>
		</spawn>
		<spawn x="11" y="5">
			<entity type="12006" variant="0" subtype="0" weight="1.0"/>
		</spawn>
		<spawn x="12" y="5">
			<entity type="12006" variant="0" subtype="0" weight="1.0"/>
		</spawn>
		<spawn x="3" y="6">
			<entity type="12006" variant="0" subtype="48" weight="1.0"/>
		</spawn>
		<spawn x="4" y="6">
			<entity type="12002" variant="137" subtype="211" weight="1.0"/>
		</spawn>
		<spawn x="5" y="6">
			<entity type="12006" variant="0" subtype="0" weight="1.0"/>
		</spawn>
		<spawn x="6" y="6">
			<entity type="12006" variant="0" subtype="0" weight="1.0"/>
		</spawn>
		<spawn x="7" y="6">
			<entity type="12002" variant="137" subtype="1251" weight="1.0"/>
		</spawn>
		<spawn x="8" y="6">
			<entity type="12006" variant="0" subtype="0" weight="1.0"/>
		</spawn>
		<spawn x="9" y="6">
			<entity type="12006" variant="0" subtype="0" weight="1.0"/>
		</spawn>
		<spawn x="10" y="6">
			<entity type="12006" variant="0" subtype="0" weight="1.0"/>
		</spawn>
		<spawn x="11" y="6">
			<entity type="12006" variant="0" subtype="0" weight="1.0"/>
		</spawn>
		<spawn x="12" y="6">
			<entity type="12006" variant="0" subtype="0" weight="1.0"/>
		</spawn>
	</room>
	<room variant="9" name="Ferrium - PILGRIMAGE TO THE SUN" type="1" subtype="0" shape="1" width="13" height="7" difficulty="15" weight="1.0">
		<door exists="False" x="-1" y="3"/>
		<door exists="False" x="6" y="-1"/>
		<door exists="False" x="6" y="7"/>
		<door exists="False" x="13" y="3"/>
		<spawn x="4" y="-1">
			<entity type="12005" variant="1" subtype="5" weight="1.0"/>
		</spawn>
		<spawn x="5" y="-1">
			<entity type="12005" variant="1" subtype="6" weight="1.0"/>
		</spawn>
		<spawn x="6" y="-1">
			<entity type="12005" variant="1" subtype="7" weight="1.0"/>
		</spawn>
		<spawn x="7" y="-1">
			<entity type="12005" variant="1" subtype="8" weight="1.0"/>
		</spawn>
		<spawn x="8" y="-1">
			<entity type="12005" variant="1" subtype="9" weight="1.0"/>
		</spawn>
		<spawn x="2" y="0">
			<entity type="12006" variant="0" subtype="0" weight="1.0"/>
		</spawn>
		<spawn x="3" y="0">
			<entity type="12006" variant="0" subtype="0" weight="1.0"/>
		</spawn>
		<spawn x="4" y="0">
			<entity type="12006" variant="0" subtype="0" weight="1.0"/>
		</spawn>
		<spawn x="5" y="0">
			<entity type="12004" variant="2943" subtype="321" weight="1.0"/>
		</spawn>
		<spawn x="6" y="0">
			<entity type="12004" variant="3715" subtype="322" weight="1.0"/>
		</spawn>
		<spawn x="7" y="0">
			<entity type="12004" variant="2943" subtype="323" weight="1.0"/>
		</spawn>
		<spawn x="8" y="0">
			<entity type="12006" variant="0" subtype="0" weight="1.0"/>
		</spawn>
		<spawn x="9" y="0">
			<entity type="12006" variant="0" subtype="0" weight="1.0"/>
		</spawn>
		<spawn x="10" y="0">
			<entity type="12006" variant="0" subtype="0" weight="1.0"/>
		</spawn>
		<spawn x="3" y="1">
			<entity type="12006" variant="0" subtype="0" weight="1.0"/>
		</spawn>
		<spawn x="4" y="1">
			<entity type="12006" variant="0" subtype="0" weight="1.0"/>
		</spawn>
		<spawn x="6" y="1">
			<entity type="12006" variant="0" subtype="53" weight="1.0"/>
		</spawn>
		<spawn x="8" y="1">
			<entity type="12006" variant="0" subtype="0" weight="1.0"/>
		</spawn>
		<spawn x="9" y="1">
			<entity type="12006" variant="0" subtype="0" weight="1.0"/>
		</spawn>
		<spawn x="1" y="2">
			<entity type="12000" variant="0" subtype="1302" weight="1.0"/>
			<entity type="199" variant="20" subtype="0" weight="1.0"/>
		</spawn>
		<spawn x="3" y="2">
			<entity type="12006" variant="0" subtype="0" weight="1.0"/>
		</spawn>
		<spawn x="4" y="2">
			<entity type="12006" variant="0" subtype="0" weight="1.0"/>
		</spawn>
		<spawn x="8" y="2">
			<entity type="12006" variant="0" subtype="0" weight="1.0"/>
		</spawn>
		<spawn x="9" y="2">
			<entity type="12006" variant="0" subtype="0" weight="1.0"/>
		</spawn>
		<spawn x="11" y="2">
			<entity type="199" variant="20" subtype="0" weight="1.0"/>
		</spawn>
		<spawn x="3" y="3">
			<entity type="12006" variant="0" subtype="0" weight="1.0"/>
		</spawn>
		<spawn x="4" y="3">
			<entity type="12006" variant="0" subtype="0" weight="1.0"/>
		</spawn>
		<spawn x="8" y="3">
			<entity type="12006" variant="0" subtype="0" weight="1.0"/>
		</spawn>
		<spawn x="9" y="3">
			<entity type="12006" variant="0" subtype="0" weight="1.0"/>
		</spawn>
		<spawn x="2" y="4">
			<entity type="12006" variant="0" subtype="0" weight="1.0"/>
		</spawn>
		<spawn x="3" y="4">
			<entity type="12006" variant="0" subtype="0" weight="1.0"/>
		</spawn>
		<spawn x="6" y="4">
			<entity type="12001" variant="0" subtype="0" weight="1.0"/>
		</spawn>
		<spawn x="9" y="4">
			<entity type="12006" variant="0" subtype="0" weight="1.0"/>
		</spawn>
		<spawn x="10" y="4">
			<entity type="12006" variant="0" subtype="0" weight="1.0"/>
		</spawn>
		<spawn x="2" y="5">
			<entity type="12006" variant="0" subtype="0" weight="1.0"/>
		</spawn>
		<spawn x="3" y="5">
			<entity type="12006" variant="0" subtype="0" weight="1.0"/>
		</spawn>
		<spawn x="9" y="5">
			<entity type="12006" variant="0" subtype="0" weight="1.0"/>
		</spawn>
		<spawn x="10" y="5">
			<entity type="12006" variant="0" subtype="0" weight="1.0"/>
		</spawn>
		<spawn x="1" y="6">
			<entity type="12006" variant="0" subtype="0" weight="1.0"/>
		</spawn>
		<spawn x="2" y="6">
			<entity type="12006" variant="0" subtype="0" weight="1.0"/>
		</spawn>
		<spawn x="3" y="6">
			<entity type="12006" variant="0" subtype="0" weight="1.0"/>
		</spawn>
		<spawn x="4" y="6">
			<entity type="12004" variant="132" subtype="261" weight="1.0"/>
		</spawn>
		<spawn x="5" y="6">
			<entity type="12004" variant="132" subtype="262" weight="1.0"/>
		</spawn>
		<spawn x="6" y="6">
			<entity type="12004" variant="132" subtype="263" weight="1.0"/>
		</spawn>
		<spawn x="7" y="6">
			<entity type="12004" variant="132" subtype="264" weight="1.0"/>
		</spawn>
		<spawn x="8" y="6">
			<entity type="12004" variant="132" subtype="265" weight="1.0"/>
		</spawn>
		<spawn x="9" y="6">
			<entity type="12006" variant="0" subtype="0" weight="1.0"/>
		</spawn>
		<spawn x="10" y="6">
			<entity type="12006" variant="0" subtype="0" weight="1.0"/>
		</spawn>
		<spawn x="11" y="6">
			<entity type="12006" variant="0" subtype="0" weight="1.0"/>
		</spawn>
		<spawn x="5" y="7">
			<entity type="12005" variant="1" subtype="1" weight="1.0"/>
		</spawn>
		<spawn x="6" y="7">
			<entity type="12005" variant="1" subtype="2" weight="1.0"/>
		</spawn>
		<spawn x="7" y="7">
			<entity type="12005" variant="1" subtype="3" weight="1.0"/>
		</spawn>
	</room>
	<room variant="10" name="Ferrium - SYMPHONY OF TWO STRINGS" type="1" subtype="0" shape="1" width="13" height="7" difficulty="10" weight="0.5">
		<door exists="False" x="-1" y="3"/>
		<door exists="False" x="6" y="-1"/>
		<door exists="False" x="6" y="7"/>
		<door exists="False" x="13" y="3"/>
		<spawn x="2" y="0">
			<entity type="12004" variant="4481" subtype="386" weight="1.0"/>
		</spawn>
		<spawn x="3" y="0">
			<entity type="12006" variant="0" subtype="0" weight="1.0"/>
		</spawn>
		<spawn x="9" y="0">
			<entity type="12006" variant="0" subtype="0" weight="1.0"/>
		</spawn>
		<spawn x="10" y="0">
			<entity type="12004" variant="4488" subtype="387" weight="1.0"/>
		</spawn>
		<spawn x="1" y="1">
			<entity type="12004" variant="4481" subtype="385" weight="1.0"/>
		</spawn>
		<spawn x="3" y="1">
			<entity type="12005" variant="1" subtype="2" weight="1.0"/>
		</spawn>
		<spawn x="4" y="1">
			<entity type="12006" variant="0" subtype="0" weight="1.0"/>
		</spawn>
		<spawn x="6" y="1">
			<entity type="12000" variant="0" subtype="803" weight="1.0"/>
		</spawn>
		<spawn x="8" y="1">
			<entity type="12006" variant="0" subtype="0" weight="1.0"/>
		</spawn>
		<spawn x="9" y="1">
			<entity type="12005" variant="1" subtype="3" weight="1.0"/>
		</spawn>
		<spawn x="11" y="1">
			<entity type="12004" variant="4488" subtype="388" weight="1.0"/>
		</spawn>
		<spawn x="0" y="2">
			<entity type="12004" variant="4481" subtype="384" weight="1.0"/>
		</spawn>
		<spawn x="2" y="2">
			<entity type="12005" variant="1" subtype="1" weight="1.0"/>
		</spawn>
		<spawn x="5" y="2">
			<entity type="12006" variant="0" subtype="0" weight="1.0"/>
		</spawn>
		<spawn x="6" y="2">
			<entity type="12006" variant="0" subtype="0" weight="1.0"/>
		</spawn>
		<spawn x="7" y="2">
			<entity type="12006" variant="0" subtype="0" weight="1.0"/>
		</spawn>
		<spawn x="10" y="2">
			<entity type="12005" variant="1" subtype="4" weight="1.0"/>
		</spawn>
		<spawn x="12" y="2">
			<entity type="12004" variant="4488" subtype="389" weight="1.0"/>
		</spawn>
		<spawn x="0" y="3">
			<entity type="12006" variant="0" subtype="0" weight="1.0"/>
		</spawn>
		<spawn x="1" y="3">
			<entity type="12005" variant="1" subtype="0" weight="1.0"/>
		</spawn>
		<spawn x="6" y="3">
			<entity type="12006" variant="0" subtype="0" weight="1.0"/>
		</spawn>
		<spawn x="11" y="3">
			<entity type="12005" variant="1" subtype="5" weight="1.0"/>
		</spawn>
		<spawn x="12" y="3">
			<entity type="12006" variant="0" subtype="0" weight="1.0"/>
		</spawn>
		<spawn x="0" y="4">
			<entity type="12006" variant="0" subtype="0" weight="1.0"/>
		</spawn>
		<spawn x="1" y="4">
			<entity type="12006" variant="0" subtype="0" weight="1.0"/>
		</spawn>
		<spawn x="11" y="4">
			<entity type="12006" variant="0" subtype="0" weight="1.0"/>
		</spawn>
		<spawn x="12" y="4">
			<entity type="12006" variant="0" subtype="0" weight="1.0"/>
		</spawn>
		<spawn x="2" y="5">
			<entity type="12006" variant="0" subtype="0" weight="1.0"/>
		</spawn>
		<spawn x="6" y="5">
			<entity type="12001" variant="0" subtype="0" weight="1.0"/>
		</spawn>
		<spawn x="10" y="5">
			<entity type="12006" variant="0" subtype="0" weight="1.0"/>
		</spawn>
		<spawn x="3" y="6">
			<entity type="12006" variant="0" subtype="0" weight="1.0"/>
		</spawn>
		<spawn x="4" y="6">
			<entity type="12006" variant="0" subtype="0" weight="1.0"/>
		</spawn>
		<spawn x="8" y="6">
			<entity type="12006" variant="0" subtype="0" weight="1.0"/>
		</spawn>
		<spawn x="9" y="6">
			<entity type="12006" variant="0" subtype="0" weight="1.0"/>
		</spawn>
	</room>
	<room variant="11" name="Ferrium - SYMPHONY OF TWO STRINGS" type="1" subtype="0" shape="1" width="13" height="7" difficulty="10" weight="0.5">
		<door exists="False" x="-1" y="3"/>
		<door exists="False" x="6" y="-1"/>
		<door exists="False" x="6" y="7"/>
		<door exists="False" x="13" y="3"/>
		<spawn x="2" y="0">
			<entity type="12004" variant="4488" subtype="386" weight="1.0"/>
		</spawn>
		<spawn x="3" y="0">
			<entity type="12006" variant="0" subtype="0" weight="1.0"/>
		</spawn>
		<spawn x="9" y="0">
			<entity type="12006" variant="0" subtype="0" weight="1.0"/>
		</spawn>
		<spawn x="10" y="0">
			<entity type="12004" variant="4481" subtype="387" weight="1.0"/>
		</spawn>
		<spawn x="1" y="1">
			<entity type="12004" variant="4488" subtype="385" weight="1.0"/>
		</spawn>
		<spawn x="3" y="1">
			<entity type="12005" variant="1" subtype="2" weight="1.0"/>
		</spawn>
		<spawn x="4" y="1">
			<entity type="12006" variant="0" subtype="0" weight="1.0"/>
		</spawn>
		<spawn x="6" y="1">
			<entity type="12000" variant="0" subtype="803" weight="1.0"/>
		</spawn>
		<spawn x="8" y="1">
			<entity type="12006" variant="0" subtype="0" weight="1.0"/>
		</spawn>
		<spawn x="9" y="1">
			<entity type="12005" variant="1" subtype="3" weight="1.0"/>
		</spawn>
		<spawn x="11" y="1">
			<entity type="12004" variant="4481" subtype="388" weight="1.0"/>
		</spawn>
		<spawn x="0" y="2">
			<entity type="12004" variant="4488" subtype="384" weight="1.0"/>
		</spawn>
		<spawn x="2" y="2">
			<entity type="12005" variant="1" subtype="1" weight="1.0"/>
		</spawn>
		<spawn x="5" y="2">
			<entity type="12006" variant="0" subtype="0" weight="1.0"/>
		</spawn>
		<spawn x="6" y="2">
			<entity type="12006" variant="0" subtype="0" weight="1.0"/>
		</spawn>
		<spawn x="7" y="2">
			<entity type="12006" variant="0" subtype="0" weight="1.0"/>
		</spawn>
		<spawn x="10" y="2">
			<entity type="12005" variant="1" subtype="4" weight="1.0"/>
		</spawn>
		<spawn x="12" y="2">
			<entity type="12004" variant="4481" subtype="389" weight="1.0"/>
		</spawn>
		<spawn x="0" y="3">
			<entity type="12006" variant="0" subtype="0" weight="1.0"/>
		</spawn>
		<spawn x="1" y="3">
			<entity type="12005" variant="1" subtype="0" weight="1.0"/>
		</spawn>
		<spawn x="6" y="3">
			<entity type="12006" variant="0" subtype="0" weight="1.0"/>
		</spawn>
		<spawn x="11" y="3">
			<entity type="12005" variant="1" subtype="5" weight="1.0"/>
		</spawn>
		<spawn x="12" y="3">
			<entity type="12006" variant="0" subtype="0" weight="1.0"/>
		</spawn>
		<spawn x="0" y="4">
			<entity type="12006" variant="0" subtype="0" weight="1.0"/>
		</spawn>
		<spawn x="1" y="4">
			<entity type="12006" variant="0" subtype="0" weight="1.0"/>
		</spawn>
		<spawn x="11" y="4">
			<entity type="12006" variant="0" subtype="0" weight="1.0"/>
		</spawn>
		<spawn x="12" y="4">
			<entity type="12006" variant="0" subtype="0" weight="1.0"/>
		</spawn>
		<spawn x="2" y="5">
			<entity type="12006" variant="0" subtype="0" weight="1.0"/>
		</spawn>
		<spawn x="6" y="5">
			<entity type="12001" variant="0" subtype="0" weight="1.0"/>
		</spawn>
		<spawn x="10" y="5">
			<entity type="12006" variant="0" subtype="0" weight="1.0"/>
		</spawn>
		<spawn x="3" y="6">
			<entity type="12006" variant="0" subtype="0" weight="1.0"/>
		</spawn>
		<spawn x="4" y="6">
			<entity type="12006" variant="0" subtype="0" weight="1.0"/>
		</spawn>
		<spawn x="8" y="6">
			<entity type="12006" variant="0" subtype="0" weight="1.0"/>
		</spawn>
		<spawn x="9" y="6">
			<entity type="12006" variant="0" subtype="0" weight="1.0"/>
		</spawn>
	</room>
</rooms>
